smpp_gateway/__init__.py
smpp_gateway/admin.py
smpp_gateway/apps.py
smpp_gateway/client.py
smpp_gateway/models.py
smpp_gateway/monitoring.py
smpp_gateway/outgoing.py
smpp_gateway/queries.py
smpp_gateway/router.py
smpp_gateway/smpp.py
smpp_gateway/subscribers.py
smpp_gateway/utils.py
smpp_gateway/management/__init__.py
smpp_gateway/management/commands/__init__.py
smpp_gateway/management/commands/listen_mo_messages.py
smpp_gateway/management/commands/smpp_client.py
smpp_gateway/migrations/0001_initial.py
smpp_gateway/migrations/0002_mtmessagestatus.py
smpp_gateway/migrations/0003_big_pks_and_help_texts.py
smpp_gateway/migrations/0004_translations.py
smpp_gateway/migrations/0005_alter_mtmessagestatus_command_status.py
smpp_gateway/migrations/0006_message_status_indexes.py
smpp_gateway/migrations/0007_momessage_error_alter_momessage_status.py
smpp_gateway/migrations/0008_remove_mtmessage_mt_message_status_idx_and_more.py
smpp_gateway/migrations/__init__.py
smpp_gateway-1.4.2.dist-info/licenses/LICENSE
smpp_gateway-1.4.2.dist-info/METADATA
smpp_gateway-1.4.2.dist-info/WHEEL
smpp_gateway-1.4.2.dist-info/top_level.txt
smpp_gateway-1.4.2.dist-info/RECORD
