Metadata-Version: 2.4
Name: smpp_gateway
Version: 1.4.2
Summary: SMPP gateway for RapidSMS projects; based on python-smpplib.
Home-page: https://github.com/caktus/rapidsms-smpp-gateway
Author: Caktus Group
Author-email: team@caktusgroup.com
License: MIT
Classifier: Topic :: Internet :: WWW/HTTP :: Dynamic Content
Classifier: Intended Audience :: Developers
Classifier: License :: OSI Approved :: MIT License
Classifier: Programming Language :: Python
Classifier: Programming Language :: Python :: 3
Classifier: Programming Language :: Python :: 3.9
Classifier: Programming Language :: Python :: 3.10
Classifier: Programming Language :: Python :: 3.11
Classifier: Programming Language :: Python :: 3.12
Classifier: Framework :: Django
Classifier: Framework :: Django :: 4.2
Classifier: Framework :: Django :: 5.0
Classifier: Framework :: Django :: 5.1
Classifier: Framework :: Django :: 5.2
Classifier: Development Status :: 5 - Production/Stable
Classifier: Operating System :: OS Independent
License-File: LICENSE
Requires-Dist: RapidSMS>=2.0
Requires-Dist: smpplib>=2.2
Requires-Dist: psycopg2>=2.8
Requires-Dist: django<6.0,>=4.2
Dynamic: author
Dynamic: author-email
Dynamic: classifier
Dynamic: description
Dynamic: home-page
Dynamic: license
Dynamic: license-file
Dynamic: requires-dist
Dynamic: summary
